LICENSE
README.md
setup.py
dragocrypt/__init__.py
dragocrypt/dragoncrypt.py
mostafac.egg-info/PKG-INFO
mostafac.egg-info/SOURCES.txt
mostafac.egg-info/dependency_links.txt
mostafac.egg-info/top_level.txt