Metadata-Version: 2.1
Name: mostafac
Version: 1.0
Summary: For developers
Home-page: https://github.com/NovaTools4
Author: The Jordan Ghost & A7X
Author-email: Novayou0@gmail.com
License: UNKNOWN
Project-URL: Bug Tracker, https://github.com/pypa/sampleproject/issues
Keywords: dragocrypt
Platform: UNKNOWN
Classifier: Development Status :: 1 - Planning
Classifier: Intended Audience :: Developers
Classifier: Programming Language :: Python :: 3
Classifier: Operating System :: Unix
Classifier: Operating System :: MacOS :: MacOS X
Classifier: Operating System :: Microsoft :: Windows
License-File: LICENSE
